LICENSE
MANIFEST.in
Readme.rst
setup.py
warc/__init__.py
warc/test_warc.py
warc.egg-info/PKG-INFO
warc.egg-info/SOURCES.txt
warc.egg-info/dependency_links.txt
warc.egg-info/top_level.txt