Metadata-Version: 1.0
Name: warc
Version: 0.1
Summary: Python library to work with WARC files
Home-page: http://github.com/anandology/warc
Author: Anand Chitipothu
Author-email: anandology@gmail.com
License: BSD
Platform: any
Classifier: Development Status :: 4 - Beta
Classifier: Environment :: Web Environment
Classifier: Intended Audience :: Developers
Classifier: License :: OSI Approved :: BSD License
Classifier: Operating System :: OS Independent
Classifier: Programming Language :: Python
